prompt_caller/__init__.py
prompt_caller/__main__.py
prompt_caller/prompt_caller.py
prompt_caller-0.1.3.dist-info/LICENSE
prompt_caller-0.1.3.dist-info/METADATA
prompt_caller-0.1.3.dist-info/WHEEL
prompt_caller-0.1.3.dist-info/top_level.txt
prompt_caller-0.1.3.dist-info/RECORD
