Metadata-Version: 2.1
Name: prompt_caller
Version: 0.1.3
Summary: This package is responsible for calling prompts in a specific format. It uses LangChain and OpenAI API
Home-page: https://github.com/ThiNepo/prompt-caller
Author: Thiago Nepomuceno
Author-email: thiago@neps.academy
Classifier: Programming Language :: Python :: 3
Classifier: License :: OSI Approved :: MIT License
Classifier: Operating System :: OS Independent
License-File: LICENSE
Requires-Dist: pyyaml>=6.0.2
Requires-Dist: python-dotenv>=1.0.1
Requires-Dist: Jinja2>=3.1.4
Requires-Dist: langchain-openai>=0.3.5
Requires-Dist: openai>=1.63.0
Requires-Dist: pillow>=11.0.0
